rules/__init__.py
rules/flask/__init__.py
rules/flask/views.py
rules/permissions.py
rules/predicates.py
rules/py.typed
rules/rulesets.py
flask_rules-0.1.0.dist-info/LICENSE
flask_rules-0.1.0.dist-info/METADATA
flask_rules-0.1.0.dist-info/WHEEL
flask_rules-0.1.0.dist-info/RECORD
