Metadata-Version: 2.1
Name: flask-rules
Version: 0.1.0
Summary: Access rules for Flask applications, inspired by django-rules.
Home-page: https://github.com/abilian/flask-rules
Author: Abilian SAS
Author-email: sf@abilian.com
Requires-Python: >=3.10,<4.0
Classifier: Development Status :: 2 - Pre-Alpha
Classifier: Intended Audience :: Developers
Classifier: Natural Language :: English
Classifier: Programming Language :: Python :: 3
Classifier: Programming Language :: Python :: 3.10
Classifier: Programming Language :: Python :: 3.11
Classifier: Programming Language :: Python :: 3.12
Requires-Dist: flask (>=3.0.0,<4.0.0)
